poetry_git_auto_version/plugin.py
poetry_git_auto_version-1.0.0.dist-info/entry_points.txt
poetry_git_auto_version-1.0.0.dist-info/LICENSE
poetry_git_auto_version-1.0.0.dist-info/WHEEL
poetry_git_auto_version-1.0.0.dist-info/METADATA
poetry_git_auto_version-1.0.0.dist-info/RECORD
