Metadata-Version: 2.1
Name: poetry-git-auto-version
Version: 1.0.0
Summary: A Poetry plugin to auto-append commit count to git versions.
Author: Joshua Butt
Author-email: josh@joshb.in
Requires-Python: >=3.7,<4.0
Classifier: Programming Language :: Python :: 3
Classifier: Programming Language :: Python :: 3.7
Classifier: Programming Language :: Python :: 3.8
Classifier: Programming Language :: Python :: 3.9
Classifier: Programming Language :: Python :: 3.10
Requires-Dist: poetry (>=1.2,<2.0)
